validador_colab/__init__.py
validador_colab/core/__init__.py
validador_colab/core/entities/__init__.py
validador_colab/core/entities/colab_counter.py
validador_colab/core/entities/datamart_counter.py
validador_colab/core/entities/natural_one.py
validador_colab/core/entities/sakura.py
validador_colab/core/entities/smarket_counter.py
validador_colab/core/entities/validation_detail.py
validador_colab/core/errors/__init__.py
validador_colab/core/errors/divergent_data.py
validador_colab/core/errors/no_data_found.py
validador_colab/core/repositories/__init__.py
validador_colab/core/repositories/colab_counters.py
validador_colab/core/repositories/datamart_counters.py
validador_colab/core/repositories/smarket_analytics.py
validador_colab/core/usecases/__init__.py
validador_colab/core/usecases/colab_service.py
validador_colab/core/usecases/datamart_service.py
validador_colab/core/usecases/smarket_service.py
validador_colab/infra/__init__.py
validador_colab/infra/configs/__init__.py
validador_colab/infra/configs/configs.py
validador_colab/infra/database/__init__.py
validador_colab/infra/database/postgres.py
validador_colab/infra/database/postgres_controle.py
validador_colab/infra/repositories/__init__.py
validador_colab/infra/repositories/colab_counters_repository.py
validador_colab/infra/repositories/datamart_counters_repository.py
validador_colab/infra/repositories/nova consulta.txt
validador_colab/infra/repositories/smarket_analytics_repository.py
validador_colab/infra/routes/__init__.py
validador_colab/infra/routes/daily_conf.py
validador_colab/infra/utils/__init__.py
validador_colab/infra/utils/break_no_data_found.py
validador_colab/infra/utils/clean_old_data.py
validador_colab/loop/__init__.py
validador_colab/loop/first_block.py
validador_colab/loop/reprocessing_first_block.py
validador_colab/loop/second_block.py
validador_colab-1.2.0.dist-info/METADATA
validador_colab-1.2.0.dist-info/WHEEL
validador_colab-1.2.0.dist-info/RECORD
